django_friendly_captcha-0.1.13.dist-info/licenses/AUTHORS
django_friendly_captcha-0.1.13.dist-info/licenses/LICENSE
friendly_captcha/__init__.py
friendly_captcha/apps.py
friendly_captcha/fields.py
friendly_captcha/tests.py
friendly_captcha/widgets.py
friendly_captcha/locale/de/LC_MESSAGES/django.mo
friendly_captcha/locale/de/LC_MESSAGES/django.po
friendly_captcha/locale/en/LC_MESSAGES/django.mo
friendly_captcha/locale/en/LC_MESSAGES/django.po
django_friendly_captcha-0.1.13.dist-info/METADATA
django_friendly_captcha-0.1.13.dist-info/WHEEL
django_friendly_captcha-0.1.13.dist-info/top_level.txt
django_friendly_captcha-0.1.13.dist-info/RECORD
